autora/state.py
autora/experimentalist/grid.py
autora/experimentalist/pipeline.py
autora/experimentalist/random.py
autora/experimentalist/utils.py
autora/serializer/__init__.py
autora/serializer/yaml_.py
autora/utils/deprecation.py
autora/utils/dictionary.py
autora/variable/__init__.py
autora/variable/time.py
autora/workflow/__main__.py
autora_core-5.0.3.dist-info/LICENSE
autora_core-5.0.3.dist-info/METADATA
autora_core-5.0.3.dist-info/WHEEL
autora_core-5.0.3.dist-info/top_level.txt
autora_core-5.0.3.dist-info/RECORD
